[TOC]



### 数组的类型描述符

数组类型的描述符为 [Class,比如“[Ljava/lang/String;”，“[I”


### 数组的创建


数组类和普通的Java类不同。普通Java类是类加载器从class文件加载出来的，数组类是JVM 运行时生成的。

创建数组类对应的指令也与new不同：

+ 基本类型数组由 `newarray` 创建；
+ 引用类型数组由`anewarray`指令创建；
+ 多维数组由 `multianewarray` 指令创建。


### oop-klass

看一下Hotspot对于数组类 oop-klass模型的定义


```cpp


class ArrayKlass: public Klass {
  friend class VMStructs;
private:
  int      _dimension;         // n维数组.
  Klass* volatile _higher_dimension;  // 指向n+1维数组
  Klass* volatile _lower_dimension;   // 指向n-1维数组
  int      _vtable_len;        // vtable表大小
  oop      _component_mirror;  // 组件类型, as a java/lang/Class




```

```cpp
class vtableEntry;

class klassVtable : public ResourceObj {
  KlassHandle  _klass;            // my klass
  int          _tableOffset;      // offset of start of vtable data within klass
  int          _length;           // length of vtable (number of entries)

```


```cpp
class ObjArrayKlass : public ArrayKlass {
  friend class VMStructs;
 private:
  Klass* _element_klass;            // The klass of the elements of this array type
  Klass* _bottom_klass;             // The one-dimensional type (InstanceKlass or TypeArrayKlass)

```


### Java中判断两个类是否相等

java中，判断两个类是否相等，依据<loader,classname>
```java
    public static void main(String[] args) {

        String[] arr1 = {"Hello", "World"};

        String[] arr2 = new String[2];
        String[] arr3 = new String[3];
        String[][] arr4 = new String[3][4];

        System.out.println(arr1.getClass());// class [Ljava.lang.String;
        System.out.println(arr2.getClass());// class [Ljava.lang.String;
        System.out.println(arr1.getClass() == arr2.getClass());// true
        System.out.println(arr1.getClass() == arr3.getClass());// true
        System.out.println(arr4.getClass());// [[Ljava.lang.String;
        System.out.println(arr4.getClass().getName());// [[Ljava.lang.String;
    }
```


### 案例分析



```java
    public static void main(String[] args) {

        int[] a1 = new int[10]; // newarray
        String[] a2 = new String[10]; // anewarray
        int[][] a3 = new int[10][10]; // multianewarray
        int x = a1.length; // arraylength
        a1[0] = 100; // istore
        int y = a1[0]; // iaload
        a2[0] = "abc"; // aastore
        String a = a2[0]; // aaload
    }
```


+ newarray：创建基本类型一维数组
+ anewarray: 创建 引用类型数组
+ multianewarray： 多维数组


```java
    public void test() {
        int[][][] x = new int[3][4][5];
    }
```


```
       0: iconst_3
       1: iconst_4
       2: iconst_5
       3: multianewarray #2,  3             // class "[[[I"
       7: astore_1
       8: return
```




### 重写instance of 规则：


+ If S is 非数组 class, then:
  * If T is class , then S == T, or S is subclass of T;
  * If T is interface , then S implement interface T.
+ If S is interface, then:
  * If T is class, then T == Object.
  * If T is interface, then T == S or is superinterface of S.
+ If S is 数组类，组件类型为SC, then:
  * If T is class, then T == Object.
  * If T is interface type, then T must be one of the interfaces implemented by arrays (JLS §4.10.3).
  * If T is an array type TC[], that is, an array of components of type TC, then one of the following must be true:
    + TC and SC are the same primitive type.
    + TC and SC are reference types, and type SC can be cast to TC
by these run-time rules.


### 案例对应的字节码跟踪

```
 0: bipush        10  // opStack:10
 2: newarray       int //opStack:ref
 4: astore_1          // a1, opStack:;
 5: bipush        10  // opStack:10
 7: anewarray     #3  // opStack:ref ,class java/lang/String
10: astore_2        // a2=ref, opStack:;
11: bipush        10  // opStack:10
13: bipush        10  // opStack:10
15: multianewarray #4,  2 // opStack:ref,class "[[I"
19: astore_3        // a3,opStack:;
20: aload_1         // opStack:a1
21: arraylength     // opStack:10
22: istore        4 // x:10, opStack:;
24: aload_1         // opStack:a1
25: iconst_0        // opStack:a1,0
26: bipush        100 // opStack:a1,0,100
28: iastore         // a[0]=100
29: aload_1         // opStack:a1
30: iconst_0        // opStack:a1,0
31: iaload          // opStack:100
32: istore        5 // y=100,opStack:;
34: aload_2         // opStack:a2
35: iconst_0        //opStack:a2,0
36: ldc           #5 //  String abc
38: aastore
39: aload_2
40: iconst_0
41: aaload
42: astore        6
44: getstatic     #6                  // Field java/lang/System.out:Ljava/io/PrintStream;
47: aload_1
48: iconst_0
49: iaload
50: invokevirtual #7                  // Method java/io/PrintStream.println:(I)V
53: getstatic     #6                  // Field java/lang/System.out:Ljava/io/PrintStream;
56: aload_2
57: iconst_0
58: aaload
59: invokevirtual #8                  // Method java/io/PrintStream.println:(Ljava/lang/String;)V
62: getstatic     #6                  // Field java/lang/System.out:Ljava/io/PrintStream;
65: aload_3
66: iconst_0
67: aaload
68: iconst_0
69: iaload
70: invokevirtual #7                  // Method java/io/PrintStream.println:(I)V
73: getstatic     #6                  // Field java/lang/System.out:Ljava/io/PrintStream;
76: iload         4
78: invokevirtual #7                  // Method java/io/PrintStream.println:(I)V
81: return

```



### String


+ 实现字符串池
+ 实现字符串打印




```java
public final class String
    implements java.io.Serializable, Comparable<String>, CharSequence {
    /** The value is used for character storage. */
    private final char value[];

    /** Cache the hash code for the string */
    private int hash; // Default to 0

    public String(char value[]) {
        this.value = Arrays.copyOf(value, value.length);
    }

    public native String intern();

```



