
[TOC]

## 方法调用和返回


方法调用，从调用方式上划分：

+ 静态方法：通过类调用，编译时已知
+ 动态方法：动态绑定，运行时可知


方法分类：

+ 没有实现的方法：抽象方法
+ native方法
+ JVM 原生语言实现的方法（Java，Scala，Groovy）



JDK7之前，提供了四条方法调用指令：

+ invokevirtual 用于调用对象的实例方法，根据对象的实际类型进行分派。
+ invokeinterface 用于调用接口方法，它会在运行时搜索一个实现了这个接口方法的对象，找出适合的方法进行调用
+ invokespecial 用于调用一些需要特殊处理的实例方法，包括实例初始化方法，私有方法和父类方法

+ invokestatic 用于调用类方法

JDK7，提供：

+ invokedynamic 用于在运行时动态解析出调用点限定符所使用的方法，并执行该方法。



方法调用需要，n+1个操作数，第一个为 u16的索引，通过它能在运行时常量池找到一个方法引用，解析这个方法引用就可以得到一个方法。 需要注意的是，这个方法并不一定就是最终调用的方法，可能还需要一个查找过程才能找到最终要调用的方法。剩下的n个操作数，从opStack中弹出。



如果要执行的是一个Java方法：

1. 给方法创建新的frame，推入ThreadStack栈顶
2. 传递参数
3. 执行函数
4. 返回结果


return指令负责将执行结果 推入前一个frame 的操作数栈。然后把当前frame从虚拟机中弹出。


不讨论接口的静态方法和默认方法。






### 方法描述符



基本字段描述符：


|FieldType term |Type |Interpretation
|:-:|:-|:-|
|B |byte |signed byte
|C |char | UTF-16
|D |double |double-precision floating-point value
|F |float |single-precision floating-point value
|I |int |integer
|J |long |long integer
|LClassName;|reference |an instance of class ClassName
|S |short |signed short
|Z |boolean |true or false
|[ |reference |one array dimension



```java
Object m(int i, double d, Thread t) {...}
//描述符 (IDLjava/lang/Thread;)Ljava/lang/Object;
```


### 测试用例




```java
public class ClassDemo {

    private int id;
    private static int times = 1;


    private ClassDemo() {
        times++;
    }

    public ClassDemo(int id) {
        this();
        this.id = id;
    }

    public static void main(String[] args) {

        ClassDemo zlass = new ClassDemo(9);

        System.out.println(tag);
        System.out.println(times);
        // System.out.println("msg:" + zlass.msg);

    }
}
```

对应的字节码：

```

public static void main(java.lang.String[])
     0: new           #5                  // opStack: ref ->
     3: dup                               // opStack:ref ref->
     4: ldc           #6                  // Push "Test msg" from cp to opStack
     6: invokespecial #7                  // Method "<init>":(Ljava/lang/String;)V
        ClassDemo.<init>(String):
             1 aload_0
             4 invoke_special
            ClassDemo.<init>(): 
                 1 aload_0 
                 4 invoke_special           // Method "<init>":()V
                Object.<init>(): 
                     1 return
                 7 getstatic
                 8 iconst_1
                 9 iadd
                 12 putstatic
                 13 return
            5 aload_0
            6 aload_1
            9 putfield
            10 return 
     9: astore_1                          // opStack： ref-> :: opStack:->
    10: getstatic     #8                  // Field java/lang/System.out:Ljava/ioPrintStream;
    13: getstatic     #2                  // Field times:I
    16: invokevirtual #9                  // Method java/io/PrintStream.println:(IV
    19: return
```




```java
public class FibonacciTest {
    public static void main(String[] args) {
        long x = fibonacci(3);
        System.out.println(x);//
    }

    private static long fibonacci(long n) {
        if (n < 3) {
            return n;
        }
        return fibonacci(n - 1) + fibonacci(n - 2);
    }
}
```


```
FibonacciTest.main() 
    # 3 ldc2_w &{{2 {}}}        // 从运行时常量池加载 long(3),push 
    # 6 invoke_static &{{4 {}}} // 调用静态方法
    FibonacciTest.fibonacci() 
        # 1 lload_0 &{{}}       // 局部变量表加载到栈顶：opStack:n=3
        # 4 ldc2_w &{{2 {}}}    // load from rtCP,opStack:L3,L3
        # 5 lcmp &{{}}          // n==3?  0
        # 8 ifge &{{5}}         // 0>=0
        #11 lload_0 &{{}}       // opStack: n=3
        #12 lconst_1 &{{}}      // opStack: L3,L1
        #13 lsub &{{}}          // opStack L2
        #16 invoke_static &{{4 {}}} // 调用 f(2)
            # 1 lload_0 &{{}}       //opStack:2
            # 4 ldc2_w &{{2 {}}}    //opStack:L2，L3
            # 5 lcmp &{{}}          //
            # 8 ifge &{{5}}
            # 9 lload_0 &{{}}       // opStack:2
            #10 lreturn &{{}}       // return 2
        #17 lload_0 &{{}}           // opStack:n=3
        #20 ldc2_w &{{7 {}}}        // 
        #21 lsub &{{}}
        #24 invoke_static &{{4 {}}}
            # 1 lload_0 &{{}}
            # 4 ldc2_w &{{2 {}}}
            # 5 lcmp &{{}}
            # 8 ifge &{{5}}
            # 9 lload_0 &{{}}
            #10 lreturn &{{}}
        #25 ladd &{{}}
        #26 lreturn &{{}}
    # 7 istore_1 &{{}}
    #10 getstatic &{{5 {}}}

```


把n改为30，运行一下，还是可以的，不过效率有点低。。



### clinit


\<clinit\> 是由编译器自动收集类中的所有类变量的初始赋值和静态代码块语句，合并生成的。语句的顺序由源文件中的顺序决定。

clinit 的调用时机：第一次需要这个类的时候

+ 第一次 `new` 对象
+ 执行 `putstatic` , `getstatic` 操作静态属性 
+ `invokestatic` 调用静态方法
+ 通过反射 操作，间接操作属性或方法

当操作一个类时，如果他的超类还没有被初始化，递归初始化之。





回过头，看一下pc到底指向了谁

thread.pc,init:0，指令执行前，指向下一个要执行的代码，指令执行结束，下一回合未开始前，指向已完成的代码。
frame.nextPC,init:0,指令执行前，nextPC指向将要执行的代码，指令执行完，下一个指令循环开始前，nextPC更新，保证指向下一个要执行的code，所以nextPC保证时刻指向下一个要执行的指令（在非指令执行阶段）

所以，当要撤销执行指令时，如果指令还没有执行，但是读取了指令码，frame.nextPC要先回退到 thread.pc

























