
[TOC]

## 本地方法调用

### 本地方法

OpenJDK 类库的本地方法是用JNI (Java Native Interface) 编写的，JVMS 并没有规定如何实现和调用本地方法，让我们有更多的想象空间。


有点意思的是，__native 方法可以被Override__




```java

public class Object {

    private static native void registerNatives();
    static {
        // 调用 JVM的函数，让jvm注册 native函数
        registerNatives();
    }
```



本次实现不支持JNI，直接用GO实现部分本地方法。在本地实现一个 本地方法注册表，由于本次实现的方法比较少，直接在启动后加载全部native方法到注册表。

本地方法 并没有字节码，JVM预留了两条指令：0xFE,0xFF。


当调用函数时，如果找到的是一个native函数，由于native函数没有code Attribute，我们给他注入 方法体为{invoke_native,Xreturn}

本次实现，自定义一条指令： invoce_native:0xFE。 每次执行invoke_native 就到native方法注册表中执行具体的方法。Xreturn 根据函数描述符中的返回值对应。


### 基本类型类的加载

+ 每个基本类型对应一个类
+ void 和基本类型的类名就是 void，int...
+ 基本类型没有超类，没有实现任何接口
+ 非基本类型的类对象是通过LDC 指令加载到操作数栈的
+ 基本类型是通过GetStatic



每个基本类型都有对应的包装类：

```java
public final class Integer extends Number implements Comparable<Integer> {

    @SuppressWarnings("unchecked")
    public static final Class<Integer>  TYPE = (Class<Integer>) Class.getPrimitiveClass("int");

    private final int value;    
```



实现

```java
    private static native Class<?> forName0(String name, boolean initialize,
                                            ClassLoader loader,
                                            Class<?> caller)
        throws ClassNotFoundException;
    
    public native boolean isAssignableFrom(Class<?> cls);

    public native boolean isInterface();
    // 断言
    private static native boolean desiredAssertionStatus0(Class<?> clazz);
```

### 反射



```java
    System.out.println(void.class.getName());// void
```
对应的指令：

```
 0: getstatic     #2    // opStack: out, 
 3: getstatic     #3    // opStack: void.class(oop)
 6: invokevirtual #4    // getName, Class.getName:()String;
 9: invokevirtual #5    // println(stirng)
12: return
```

void.class 是一个实例，也就是instanceOop。对应Void类里的 TYPE 。他的类型是Class，不代表元数据。

```java
public final
class Void {

    // 这里是一个oop 对象
    @SuppressWarnings("unchecked")
    public static final Class<Void> TYPE = (Class<Void>) Class.getPrimitiveClass("void");

    /*
     * The Void class cannot be instantiated.
     */
    private Void() {}
}
```

void.class.getName() 调用的是Class 类的native方法

```java
public final class Class<T> implements java.io.Serializable,
                              GenericDeclaration,
                              Type,
                              AnnotatedElement {
    public String getName() {
        String name = this.name;
        if (name == null)
            this.name = name = getName0();
        return name;
    }
    private native String getName0();
}
```

### JAVA 类库


#### String 加法 和 StringBuilder

String 类的初始化时机：

+ 第一次用到，
+ 第一次 执行new
+ 第一次静态调用属性或方法




```java
    public static void main(String[] args) {

        String v1="Hello";
        String v2="wrold";

        String v3=v1+v2;
        System.out.println(v3);
    }
```

```code
  public static void main(java.lang.String[]);
    descriptor: ([Ljava/lang/String;)V
    flags: ACC_PUBLIC, ACC_STATIC
    Code:
      stack=2, locals=4, args_size=1
         0: ldc           #3                  // opStack: String("Hello");
         2: astore_1                          // v1="Hello", opStack:;
         3: ldc           #4                  // opStack：String(wrold)
         5: astore_2                          // v2="world",opStack:;
         6: new           #5                  // class java/lang/StringBuilder
         9: dup                               // opStack: builder,builder
        10: invokespecial #6                  // builder."<init>":()V
        13: aload_1                           // opStack:builder,v1;
        14: invokevirtual #7                  // builder=builder.append(v1),opStack:builder;
        17: aload_2                           // opStack:builder,v2
        18: invokevirtual #7                  // opStack:builder
        21: invokevirtual #8                  // builder, "Hello wrold"
        24: astore_3                          // 
        25: getstatic     #9                  // Field java/lang/System.out:Ljava/io/PrintStream;
        28: aload_3
        29: invokevirtual #10                 // Method java/io/PrintStream.println:(Ljava/lang/String;)V
        32: return
}
```

从反编译的源码来看，真实的源码是这样的：

```java
    public static void main(String[] args) {

        String v1="Hello";
        String v2="wrold";

        String v3=new StringBuilder().append(v1).append(v2).toString();
        System.out.println(v3);
    }
```
这里注意 变量的的命名也是故意的
+ v1表示对应局部变量表（locals） 的第一个槽位。
+ locals[0]就是args



然后详细再看下去，先看 `StringBuilder` 的 `<init>()V` 函数


```java
public final class StringBuilder 
    extends AbstractStringBuilder
    implements java.io.Serializable, CharSequence

    public StringBuilder() {
        super(16);
    }
...
```
父类是一个抽象类，构造时，new了一个char数组
```java
abstract class AbstractStringBuilder implements Appendable, CharSequence {

    AbstractStringBuilder(int capacity) {
        value = new char[capacity];
    }
...
```

所以默认是16长度的char[]数组，count是真实的当前长度。




再看append。

```java
    @Override
    public StringBuilder append(String str) {
        super.append(str);
        return this;
    }
```



```java
abstract class AbstractStringBuilder implements Appendable, CharSequence {

    public AbstractStringBuilder append(String str) {
        
        if (str == null)
            return appendNull();
        int len = str.length();
        // 预估 拼接后的长度是否够放，不够就扩容
        ensureCapacityInternal(count + len);
        // 把 str[0,len) copy 到 value[count,count+len)
        str.getChars(0, len, value, count);
        // 更新count
        count += len;
        return this;
    }
...
```

一步步跟踪进去，会发现 str.getChars 使用了：

```java
public final class System {
    public static native void arraycopy(Object src,  int  srcPos,
                                        Object dest, int destPos,
                                        int length);
···
```



#### StringBuilder.toString()  

对于StringBuilder.toString()，使用了 Arrays.copyOfRange 函数，然后使用了Math类，Math类的 `<clinit>` 会调用 `Float.floatToRawIntBits` 和 `Double.doubleToRawLongBits`.



```java
public final class Math {
    
    private static long negativeZeroFloatBits  = Float.floatToRawIntBits(-0.0f);
    private static long negativeZeroDoubleBits = Double.doubleToRawLongBits(-0.0d);

```



```java
public final class Float extends Number implements Comparable<Float> {

    public static native int floatToRawIntBits(float value);
...
}

public final class Double extends Number implements Comparable<Double> {

    public static native long doubleToRawLongBits(double value);
...
```


再看一个例子：

```java
    public static void main(String[] args) {

        int x = 1;
        String s = "abc" + x;
        System.out.println(s);

```

```
 Code:
      stack=2, locals=3, args_size=1
         0: iconst_1             // opStack:1
         1: istore_1             // x=1,opStack:;
         2: new           #2     // opStack:new StringBuilder
         5: dup                  // opStack:builder ,builder
         6: invokespecial #3     // builder."<init>":      opStack:builder;
         9: ldc           #4     // opStack:builder, "abc"
        11: invokevirtual #5     // builder=builder.append:("abc"); opStack:builder
        14: iload_1              // opStack:builder,x
        15: invokevirtual #6     // builder=builder,append(x),opStack:builder
        18: invokevirtual #7     // opStack:builder.toString:()
        21: astore_2             // s="abc"+x
        22: getstatic     #8     // opStack:System.out:
        25: aload_2              // opStack:out,s
        26: invokevirtual #9     // out.println:(s)
        29: return                                          
```
大致等价于代码：

```java
    public static void main(String[] args) {
        int x = 1;
        String s = new StringBuilder().append("abc").append(x);
        System.out.println(s);
    }
```



#### String.intern


```java
    // 得到字符串对应的常量池 对象
    public native String intern();
```


#### Object.clone()


```java
    protected native Object clone() throws CloneNotSupportedException;
```




#### 自动装箱

Java的自动装箱是编译时做的，对于int，编译器 注入一些代码，调用 Integer.valueOf(int) 返回一个包装对象。


```java
/**
 * 自动装箱测试
 */
public class BoxTest {
    public static void main(String[] args) {
        List<Integer> list = new ArrayList<>();
        list.add(1);
        list.add(2);
        System.out.println(list.toString());

    }
}
```

等价于：
```java
public class BoxTest {
    public static void main(String[] args) {
        List<Integer> list = new ArrayList<>();
        list.add(Integer.valueOf(1));
        list.add(Integer.valueOf(2));
        System.out.println(list.toString());
    }
}
```

从指令找证据
```java
  public static void main(java.lang.String[]);
    descriptor: ([Ljava/lang/String;)V
    flags: ACC_PUBLIC, ACC_STATIC
    Code:
      stack=2, locals=2, args_size=1
         0: new           #2                  // opStack:new ArrayList()
         3: dup                                  opStack:list,list           
         4: invokespecial #3                  // ArrayList."<init>"， opStack:list;
         7: astore_1                          // list=list, opStack:;
         8: aload_1                           // opStack:list;
         9: iconst_1                          // opStack:list,1;
        10: invokestatic  #4                  // 自动装箱 Integer.valueOf(1)，opStack:list,Int(1)
        13: invokeinterface #5,  2            // InterfaceMethod java/util/List.add:(Ljava/lang/Object;)Z
        18: pop
        19: aload_1
        20: iconst_2
        21: invokestatic  #4                  // Method java/lang/Integer.valueOf:(I)Ljava/lang/Integer;
        24: invokeinterface #5,  2            // InterfaceMethod java/util/List.add:(Ljava/lang/Object;)Z
        29: pop
        30: getstatic     #6                  // Field java/lang/System.out:Ljava/io/PrintStream;
        33: aload_1
        34: invokevirtual #7                  // Method java/lang/Object.toString:()Ljava/lang/String;
        37: invokevirtual #8                  // Method java/io/PrintStream.println:(Ljava/lang/String;)V
        40: return
```














