[TOC]



没有考虑对象压缩的问题

## 类和对象模型


GO语言中，[]Object 默认 每个item都是指针


classFile中的常量池，是一个数组的形式，每一个槽位都是对应一种file const style，是一维结构


### JVM的执行过程：

JVM 动态装载，链接，初始化类和接口。

1. Loading： 找到class文件对应的二进制数据，然后创建对应的 class 或者 interface。
2. Linking： 将class或者 interface 组合到运行时数据区，以便执行。
3. Initialization：  执行class或者 interface的初始化方法 \<clinit>

一个类在 JVM 的整个流程：

1. Loading
2. Linking
    + Verification: 验证
    + Preparation：准备
    + Resolution：解析
3. Initialization
4. Using
5. Unloading

### 运行时常量池

classfile中的常量池信息，用于在创建class或者interface时构建 run time constant pool。 运行时常量池存放所有的`符号引用(symbolic reference)`。 

运行时常量池包括以下的符号引用：

+ A symbolic reference to a `class` or `interface` is derived from a `CONSTANT_Class_info` structure。
+ A symbolic reference to a `field` of a class or an interface is derived from a `CONSTANT_Fieldref_info` structure 
+ A symbolic reference to a `method` of a class is derived from a `CONSTANT_Methodref_info` structure
+ A symbolic reference to a `method` of an interface is derived from a `CONSTANT_InterfaceMethodref_info` structure
+ A symbolic reference to a `method handle` is derived from a `CONSTANT_MethodHandle_info` structure
+ A symbolic reference to a method type is derived from a `CONSTANT_MethodType_info` structure
+ A symbolic reference to a `call site specifier` is derived from a `CONSTANT_InvokeDynamic_info` structure


这些是符号引用，构建运行时常量池时，只会加载符号引用，还不会加载符号引用关联的类

一些 非符号引用，是利用 file 的 constant_pool table 找到的

+ 运行时常量，对应 CONSTANT_Integer_info,CONSTANT_Float_info, CONSTANT_Long_info, or CONSTANT_Double_info

+ 一个 string字面量对应 CONSTANT_String_info structure. 


Java 规定， 完全相同的字面量 必须指向同一个 String实例。另外，如果 String.intern 调用了，任何相同内容的string的调用结果都指向同一个String实例。

```java
("a" + "b" + "c").intern() == "abc"
```

也就说，对于String.intern：

+ 如果常量池中已经定义对应的常量，直接返回引用
+ 如果不存在对应的常量，将会在常量池创建常量并 返回常量池对应的指针


其余的常量对应，如 `CONSTANT_NameAndType_info` 和 `CONSTANT_Utf8_info` 只会间接使用，用于 处理 class，interfaces,methods,fields,method types，method handles等，还有处理 字符串字面量。





### JVM Startup

+ JVM通过使用bootstrap-ClassLoader 创建一个初始类，来启动
+ 然后，JVM 初始化 link 这个初始 class, 
+ 初始化 他 
+ 调用 public class method void main(String[]).
    + 可能会导致加载其他的类


这个初始类，一般就是我们 在命令行参数中给出的。






### Creation and Loading

根据全限定名称 N 创建 一个 class/interface C ，包括在 method-area 中构建 C 对应的结构。class/interface 的创建又由 另一个 interface/class D 的创建所触发，D 通过其运行时常量池中的`符号引用` 关联到 C。

+ 如果C 不是一个数组类， 由 classLoader 加载 C 对应的二进制数据创建。
+ 数组类没有 具体的二进制表示，他们由JVM创建，而不是类加载器。

class/interface 的创建也可以是由于调用lib库中的反射相关方法，直接创建




#### 两种 class loaders: 

+ 由JVM实现 并默认支持的 bootstrap class loader
+ 用户自定义的 user-defined class loaders. 

每一个user-defined class loader都是 抽象类ClassLoader的子类的一个实例。应用程序使用 user-define 来扩展 JVM动态加载和创建类。User-define class loader 可以用于从用户定义的源来创建class。例如从加密的文件，从网络下载等。

一个类C的创建，即可以由类加载器 L 直接加载，也可以由 L 委托其他加载器加载。 这时候视为 L 启动了 C 的加载。


#### 数组和非数组类的创建

D 触发C的创建，根据全限定名 N 创建 C ：

+ 如果是非数组，两种方式：
    + 如果D是 Boot-ClassLoader创建的，C也由它创建
    + 如果D是 用户自定义ClassLoader ：L创建的，C由L创建
+ 如果是数组
    + 由JVM负责创建对应的数组类
    + 过程中，需要使用到 D 的 ClassLoader

当加载过程出现错误，在 已加载类（触发此次加载的）的程序执行点 抛出一个 LinkageError 的子类实例。

#### 一个 行为良好的 类加载器 的特点

JVMS 对于一个行为良好的 类加载器的三点要求：

+ 给出同一个name，每次返回必须是同一个Class Object
+ 如果 $L_1$ 委托$L_2$加载C，对于 C的T： C的直接父类、直接父接口、或者属性相关联的类、或者函数参数关联的类、或者返回类型，L1和L2需要返回同样的Class object。
+ If a user-defined classloader prefetches binary representations of classes and interfaces, or loads a group of related classes together, then it must reflect loading errors only at points in the program where they could have arisen without prefetching or group loading.

一般的，对于 $L_d$ 直接加载了C，记为 $<N, L_d>$, 或者 $N^{L_d}$

#### 使用 Bootstrap-ClassLoader 加载

1. JVM 判断 Boot-ClassLoader是不是已经被指定为N对应的class/interface 的一个初始加载器（已经加载了），是，则直接返回
2. 否则，JVM 通过N，搜索目标 表示（可能为class文件）
3. 如果没有找到，抛出ClassNotFoundException.



Then the Java Virtual Machine attempts to `derive a class` denoted by N using the bootstrap class loader from the purported representation using the algorithm found in §5.3.5. That class is C.

这里说的就是 依据classfile 产生对应的 class 运行时形态，也就是klass


#### 使用 用户定义的类加载器 加载

1. L 是否已加载了N对应的C，是，直接返回C
2. 否则，调用L.loadClass(N), 返回C
    + 根据 bytes 创建ClassFile 结构，之后必须调用defineClass ,产生具体的C
    + L可以委托 $L'$ loadClass





#### 创建 数组类


使用 L ，根据N创建 array class C,L可以是boot-classLoader或者 user-ClassLoader

如果已加载，直接返回，否则：

1. 如果item是 ref 类型，调用 ref 的解析逻辑(使用 L)
2. JVM 根据 组件类型和 维度信息，创建 数组类

如果 item 是ref类型，C必须由 $L^{item}$ 定义，否则，C必须定义在Boot-ClassLoader上

如果是ref， accessibility 是由组件类型决定的，否则，是public


#### 加载约束


$N^{L_1} = N^{L_2}$ 在某段时间，JVM认为 一个加载器是C的初始加载器，然后，JVM马上检查 加载约束，如果违反约束，抛出LinkageError,取消 C的记录

违反加载约束，当且仅当 下面四个条件同时满足：

+ 存在 L 是 N对应的C的初始加载器
+ 存在 L' 是 N对应的C'的初始加载器
+ 等价于 $N^L=N^{L'}$
+ $C \neq C'$


没怎么看懂JVMS为什么要写成四句，就是 对于同一个N，不同加载器加载的，属于两个不同的类，不就完了吗


#### 从ClassFile 生成 Class 

根据 ClassFile结构，使用L，获得对应的Class运行时结构

1. 如果 N在L已加载，直接 抛出 LinkageError.
2. 否则，根据N解析，得到C
    + 如果 ClassFile结构不符合规范，抛出 ClassFormatError.
    + 如果主副版本 不支持，抛出 UnsupportedClassVersionError.
    + 否则，也就是C实际上并不能表示N，抛出 NoClassDefFoundError
3. 如果C存在`直接父类`，解析对应的`符号引用`。如果C是一个接口，C必须有一个Object直接父类。只有Object没有直接父类。

    + 如果这个direct superclass 实际上是一个interface(本应是一个class)，抛出 IncompatibleClassChangeError.
    + 如果C的 direct superclass  是C，抛出  ClassCircularityError.

4. 如果 C 有一些 `direct superinterfaces`，解析对应的`符号引用`
    + 如果 interfaces这些 实际上不是接口，抛出 IncompatibleClassChangeError.
    + C 的 direct interfaces 有C，抛出 ClassCircularityError.

5. JVM 标记C的 加载器为L，L 被 JVM 认为是C的 初始加载器


### Linking

Linking a class or interface involves verifying and preparing that class or interface, its direct superclass, its direct superinterfaces, and its element type (if it is an array type), if necessary. Resolution of symbolic references in the class or interface is an optional part of linking.

link 就是  校验和准备 class 和其直接父类，直接父接口...

解析 class/interface 中的 符号引用。

#### Verification
Verification ensures that the binary representation of a class or interface is structurally correct .

确认classFile 是正确的

#### Preparation


Preparation 创建静态属性并初始化为默认值。满足一些约束。

对于 $<C,L_1>$,存在方法m,重写于父类 $<D,L_2>$，满足以下约束：

&emsp;记 m的return Type 为$T_r$，参数类型为 $T_{f_1} \dots T_{f_n}$

&emsp;&emsp;if $T_r$ 不是数组，$T_0=T_r$ 否则，$T_0 $ 是 $ElementType(T_r)$


&emsp;&emsp;For i=1 to n:
&emsp;&emsp;&emsp;&emsp;if $T_{f_i}$ not an array type:
&emsp;&emsp;&emsp;&emsp;$T_i=T_{f_i}$
&emsp;&emsp;else:
&emsp;&emsp;&emsp;&emsp;$T_i=ElementType(T_{F_i})$
&emsp;&emsp;满足 For i=0 to n:
&emsp;&emsp;&emsp;&emsp;$T_i^{L_1}=T_i^{L_2}$


对于接口的约束，参考上面，详细看JVMS文档


静态 属性的存储，对于static final Field

	// 如果属性是常量，会有一个Constant_value_attribute，其中index 指向 常量池


#### Resolution


JVMS 并未规定具体的解析时机，只要求 `anewarray`, `checkcast`, `getfield`, `getstatic`, `instanceof`, `invokedynamic`, `invokeinterface`, `invokespecial`, `invokestatic`, `invokevirtual`, `ldc`, `ldc_w`, `multianewarray`, `new`, `putfield`, and `putstatic` 这十六个用于操作符号引用的字节码指令，在执行前，先对他们所使用的符号引用进行解析。所以虚拟机实现可以根据需要来判断到底是在类加载器加载时就对常量池中的符号引用进行解析，还是等到一个符号引用将要被使用前采取解析它。

本次实现，采用`懒解析`的方式。


对同一个符号引用进行多次解析请求是常见的，除了 invokedynamic以外，JVM 可以实现对解析结果缓存（在运行时常量池中记录直接引用，并标记为已解析）。无论实际上是否执行了多次解析，JVMS规定 一次成功则后面都一定成功，也就是表现一致。

对于invokedynamic,则无法缓存。当碰到前面已经由invokedynamic触发过解析的符号引用时，并不意味着这个解析结果对于其他invokedynamic指令也同样生效。因为invokedynamic指令的本意就是用于`动态语言支持`。它所对应的引用称为`动态调用点限定符`(Dynamic Call Site Specifier)。这里的动态 的语义，就是**必须等到程序实际执行到这条指令的时候，解析动作才能执行**。相对的，其余解析指令都是静态的。可以在刚刚完成加载阶段，还没由开始执行代码时就进行解析。


`Resolution` 是从运行时常量池中的符号引用动态确定具体值的过程。

+ invokevirtual 用于调用对象的实例方法，根据对象的实际类型进行分派。
+ invokeinterface 用于调用接口方法，它会在运行时搜索一个实现了这个接口方法的对象，找出适合的方法进行调用
+ invokespecial 用于调用一些需要特殊处理的实例方法，包括实例初始化方法，私有方法和父类方法

+ invokestatic 用于调用类方法
+ invokedynamic 用于在运行时动态解析出调用点限定符所使用的方法，并执行该方法。





##### 懒解析实现



```java
public class MyObject {

    public static int staticVar;
    public int instanceVar;
    // ([Ljava/lang/String;)V
    public static void main(String[] args) {
        int x = 32768;  // idc把运行时常量池的 32768 推到栈顶，然后 istore_1 把栈顶数据 存到局部变量表
        MyObject myObj = new MyObject(); // new dup  invokespecial

        myObj.staticVar = x;
        x = myObj.staticVar;
        myObj.instanceVar = x;
        x = myObj.instanceVar;

        Object obj = myObj;
        if (obj instanceof MyObject) {
            myObj = (MyObject) obj;
            System.out.println(myObj.instanceVar);
        }
    }
}
```
// idc #2  把运行时常量池中的数据 推到操作数栈


MyObject myObj = new MyObject();  对应的指令：
+ new 指令后面跟着一个uint16， 指向一个运行时常量池的classRef，解析这个符号引用，然后创建对象，把引用推入堆顶。 + dup 堆顶加倍
+ invokespecial 后面接一个u16，指向 初始化方法 \<init>
+ astore_2 出栈，写入到 myObj
+ 把 myObj 入栈
+ 出栈


```
Code:
      stack=2, locals=4, args_size=1
         0: ldc           #2                  // int 32768
         2: istore_1
         3: new           #3                  // class MyObject
         6: dup
         7: invokespecial #4                  // Method "<init>":()V
        10: astore_2
        11: aload_2
        12: pop
        13: iload_1
        14: putstatic     #5                  // Field staticVar:I
        17: aload_2
        18: pop
        19: getstatic     #5                  // Field staticVar:I
        22: istore_1
        23: aload_2
        24: iload_1
        25: putfield      #6                  // Field instanceVar:I
        28: aload_2
        29: getfield      #6                  // Field instanceVar:I
        32: istore_1
        33: aload_2
        34: astore_3
        35: aload_3
        36: instanceof    #3                  // class MyObject
        39: ifeq          57
        42: aload_3
        43: checkcast     #3                  // class MyObject
        46: astore_2
        47: getstatic     #7                  // Field java/lang/System.out:Ljava/io/PrintStream;
        50: aload_2
        51: getfield      #6                  // Field instanceVar:I
        54: invokevirtual #8                  // Method java/io/PrintStream.println:(I)V
        57: return
```



 `anewarray`, `checkcast`, `getfield`, `getstatic`, `instanceof`, `invokedynamic`, `invokeinterface`, `invokespecial`, `invokestatic`, `invokevirtual`, `ldc`, `ldc_w`, `multianewarray`, `new`, `putfield`, and `putstatic`


new




现在的问题：

+ 没有调用\<init\>,\<clinit\>

所以对于下面的程序：

```java
public class ClassDemo {

    private static String tag = "HelloWorld";
    private static int times = 1;

    private String msg;

    private ClassDemo() {
        times++;
    }

    public ClassDemo(String msg) {
        this();
        this.msg = msg;
    }

    public static void main(String[] args) {

        ClassDemo zlass = new ClassDemo("Test msg");

        // System.out.println(tag);
        System.out.println(times);
        // System.out.println("msg:" + zlass.msg);

    }
}
```

最后times打印出来是0



### Method结构体

```cpp

class Method : public Metadata {
 friend class VMStructs;
 private:
  ConstMethod*      _constMethod;                // Method read-only data.
  MethodData*       _method_data;
  MethodCounters*   _method_counters;
  AccessFlags       _access_flags;               // Access flags
  int               _vtable_index;               // vtable index of this method (see VtableIndexFlag)
                                                 // note: can have vtables with >2**16 elements (because of inheritance)
#ifdef CC_INTERP
  int               _result_index;               // C++ interpreter needs for converting results to/from stack
#endif
  u2                _method_size;                // size of this object
  u1                _intrinsic_id;               // vmSymbols::intrinsic_id (0 == _none)
  u1                _jfr_towrite      : 1,       // Flags
                    _caller_sensitive : 1,
                    _force_inline     : 1,
                    _hidden           : 1,
                    _dont_inline      : 1,
                                      : 3;

#ifndef PRODUCT
  int               _compiled_invocation_count;  // Number of nmethod invocations so far (for perf. debugging)
#endif
  // Entry point for calling both from and to the interpreter.
  address _i2i_entry;           // All-args-on-stack calling convention
  // Adapter blob (i2c/c2i) for this Method*. Set once when method is linked.
  AdapterHandlerEntry* _adapter;
  // Entry point for calling from compiled code, to compiled code if it exists
  // or else the interpreter.
  volatile address _from_compiled_entry;        // Cache of: _code ? _code->entry_point() : _adapter->c2i_entry()
  // The entry point for calling both from and to compiled code is
  // "_code->entry_point()".  Because of tiered compilation and de-opt, this
  // field can come and go.  It can transition from NULL to not-null at any
  // time (whenever a compile completes).  It can transition from not-null to
  // NULL only at safepoints (because of a de-opt).
  nmethod* volatile _code;                       // Points to the corresponding piece of native code
  volatile address           _from_interpreted_entry; // Cache of _code ? _adapter->i2c_entry() : _i2i_entry

  // Constructor
  Method(ConstMethod* xconst, AccessFlags access_flags, int size);
```





