
## 解析器




### JVM的异常：

指令运行期间，JVM随时可以抛出 VirtualMachineError 。

+ InternalError: 一个内部的一场，由于JVM的实现问题，底层系统故障，或者硬件故障。此故障是异步分发的，可以在程序的任何节点产生。
+ OutOfMemoryError: JVM 实例 使用内存超过虚拟或者物理内存，并且自动内存管理器没办法再分配足够的内存空间来满足对象的创建需求。
+ StackOverflowError: JVM 中，一个线程的栈空间溢出，一般是由于 死循环的递归调用。
+ UnknownError: 一个异常或者错误发生，但是JVM没办法表示出具体的错误或异常，则作为默认类。


### 操作码

一个指令：


+ 一个操作码后面跟随着 0 或多个操作数
+ 链接 Exceptions,如果有对应的链接异常，可以写在里面
+ 如果有运行时异常，指令也会包含


|助记符首字母|数据类型
|:-:|:-|
|a|ref|
|b|byte|boolean|
|c|char|
|d|double|
|f|float|
|i|int|
|l|long|
|s|short|




jvm 的操作码，有一些 must和must not 的语义，比如 " The value2 must be of type int." 如果不满足这些语义，操作码的执行结果的未知的。类型的校验，JVM在Attribute中有对应的辅助数据，此处不做实现。

在link阶段，会有校验的环节，保证这些must语义




#### JVM文档的指令描述

jvm规范中，对于指令的描述，操作数栈部分时分了前后状态的：

操作前：..., arrayref, index →（栈顶）
操作后： ..., value




#### 常量指令
15条：

简单常量指令：
aconst_null
iconst_0
iconst_1
iconst_2
iconst_3
iconst_4
iconst_5
iconst_m1
lconst_0
lconst_1
fconst_0
fconst_1
fconst_2
dconst_0
dconst_1

例如：


iconst_\<i>
+ Operation; Push int constant
+ Format: iconst_\<i>
+ Forms: iconst_m1 = 2 (0x2)
    + iconst_0 = 3 (0x3)
    + iconst_1 = 4 (0x4)
    + iconst_2 = 5 (0x5)
    + iconst_3 = 6 (0x6)
    + iconst_4 = 7 (0x7)
    + iconst_5 = 8 (0x8)
+ Operand ... →
+ Stack ..., \<i>
+ Description：Push the int constant \<i> (-1, 0, 1, 2, 3, 4 or 5) onto the operand stack.


#### 扩展常量指令

bipush ：byte  扩展为int后入opStack
sipush : short 扩展为int后入opStack


#### 加载指令

从局部变量表获取变量，然后推入opStack。共 33 条，可分为6类：

+ aload : ref
    + aload index
    + aload_0 
    + aload_1 
    + aload_2 
    + aload_3 
+ dload : double
    + double index
    + dload_0
    + dload_1
    + dload_2
    + dload_3
+ fload : float
    + fload index
    + fload_0
    + fload_1
    + fload_2
    + fload_3
+ iload : int  
    + iload  index
    + iload_0 : 等价于 iload 0
    + iload_1
    + iload_2
    + iload_3
+ lload : long
    + lload index
    + lload_0
    + lload_1
    + lload_2
    + lload_3

+ xaload : array
    
    + daload :Load double from array
+ iaload...





##### 跳转指令


swtich-cace在java中有两种实现：

tableswitch和loopupswitch


tableswtich

```java

swtich(i){
    case 0: return 0;
    case 1: return 1;
    case 2: return 2;
    default: return -1;
}
```









loopupswitch

```java

swtich(i){
    case -100: return 0;
    case 0: return 1;
    case 100: return 2;
    default: return -1;
}


```


其他指令省略，详细的参考JVMS8(jvm8规范)

#### 测试用例

```java
class HelloWorld {
    HelloWorld() {
    }
    public static void main(String[] args) {
        int sum=0;
        for(int i=0;i<100;++i){
            sum+=i;
        }
        System.out.println(sum);
    }
}
```


main函数编译后的指令：

```
 Code:
       0: iconst_0      // push(0)      //stack: 0
       1: istore_1      // sum:localVar[1]=opStack.pop()= 0
       2: iconst_0      // opStack.push(0)
       3: istore_2      // i:localVar[2]=opStack.pop() =0
       4: iload_2       // push(localVar[2]) //stack:0 ->
       5: bipush        100 // opStack.push(100) //0,100
       7: if_icmpge     20  //  v2=pop 100 ,v1=pop 0// 
      10: iload_1       //push 0        // stack: 0
      11: iload_2       //push 0        // stack 0 0
      12: iadd          // pop pop push 0+0=0 // stack 0
      13: istore_1      // sum=0
      14: iinc          2, 1    // localVar[2]+=1,i=1
      17: goto          4       // 
      20: getstatic     #3                  // Field java/lang/System.out:Ljava/io/PrintStream;
      23: iload_1
      24: invokevirtual #4                  // Method java/io/PrintStream.println:(I)V
      27: return
}
```

目前能做到 for循环执行完毕，执行到循环结束会遇到不能执行的指令，退出，观察本地方法栈，可以看到循环后的sum值，在localVar[2]


```java

    public static void main(String[] args) {
        int sum = 0;
        for (int i = 100; i > 0; --i) {

            if (i % 3 == 0) {
                sum += i / 3;
            } else {
                sum += i % 3;
            }
            if ((i * 2) % 7 == 1) {
                i -= 2;
            }
        }
        System.out.println(sum);    //474
    }
```


```java
    public static void main(String[] args) {
        int sum = 0;
        for (int i = 100; i > 0; --i) {

            sum += i;
        }
        System.out.println(sum);
    }
```

const_i 把i push到栈
istore_i pop出栈顶元素，保存到局部变量表的i位置
iload_i 把 opStack.push(var[i])


javap打印日志如下：

```log
       0: iconst_0      // push 0
       1: istore_1      // var[1]=pop sum=0
       2: bipush        100     //push 100
       4: istore_2      // var[2]=pop 100,i=100
       5: iload_2       // push 100 //100
       6: ifle          19  //pop 100<=0? no
       9: iload_1       // push(sum)
      10: iload_2       // push i=100
      11: iadd          // pop pop pushsum+i
      12: istore_1      // sum=pop,sum=sum+i
      13: iinc          2, -1   // i=i-1
      16: goto          5       // goto 5,for continue
      19: getstatic     #3                  // Field java/lang/System.out:Ljava/io/PrintStream;
      22: iload_1
      23: invokevirtual #4                  // Method java/io/PrintStream.println:(I)V
      26: return
```
